{"idx":"31","name":"Japan","id":"37i9dQZEVXbKXQ4mDTEBXq","genres":[{"name":"j-pop","count":23},{"name":"anime","count":9},{"name":"j-rock","count":9}],"artists":[{"external_urls":{"spotify":"https://open.spotify.com/artist/5kVZa4lFUmAQlBogl1fkd6"},"href":"https://api.spotify.com/v1/artists/5kVZa4lFUmAQlBogl1fkd6","id":"5kVZa4lFUmAQlBogl1fkd6","name":"Aimyon","type":"artist","uri":"spotify:artist:5kVZa4lFUmAQlBogl1fkd6","count":8},{"external_urls":{"spotify":"https://open.spotify.com/artist/5Vo1hnCRmCM6M4thZCInCj"},"href":"https://api.spotify.com/v1/artists/5Vo1hnCRmCM6M4thZCInCj","id":"5Vo1hnCRmCM6M4thZCInCj","name":"Official HIGE DANdism","type":"artist","uri":"spotify:artist:5Vo1hnCRmCM6M4thZCInCj","count":6},{"external_urls":{"spotify":"https://open.spotify.com/artist/6eUKZXaKkcviH0Ku9w2n3V"},"href":"https://api.spotify.com/v1/artists/6eUKZXaKkcviH0Ku9w2n3V","id":"6eUKZXaKkcviH0Ku9w2n3V","name":"Ed Sheeran","type":"artist","uri":"spotify:artist:6eUKZXaKkcviH0Ku9w2n3V","count":3},{"external_urls":{"spotify":"https://open.spotify.com/artist/4QvgGvpgzgyUOo8Yp8LDm9"},"href":"https://api.spotify.com/v1/artists/4QvgGvpgzgyUOo8Yp8LDm9","id":"4QvgGvpgzgyUOo8Yp8LDm9","name":"Mrs. GREEN APPLE","type":"artist","uri":"spotify:artist:4QvgGvpgzgyUOo8Yp8LDm9","count":3},{"external_urls":{"spotify":"https://open.spotify.com/artist/6rs1KAoQnFalSqSU4LTh8g"},"href":"https://api.spotify.com/v1/artists/6rs1KAoQnFalSqSU4LTh8g","id":"6rs1KAoQnFalSqSU4LTh8g","name":"back number","type":"artist","uri":"spotify:artist:6rs1KAoQnFalSqSU4LTh8g","count":3},{"external_urls":{"spotify":"https://open.spotify.com/artist/6wxfx1yhyqjCPYwwxJktR2"},"href":"https://api.spotify.com/v1/artists/6wxfx1yhyqjCPYwwxJktR2","id":"6wxfx1yhyqjCPYwwxJktR2","name":"King Gnu","type":"artist","uri":"spotify:artist:6wxfx1yhyqjCPYwwxJktR2","count":2},{"external_urls":{"spotify":"https://open.spotify.com/artist/6n4SsAp5VjvIBg3s9QCcPX"},"href":"https://api.spotify.com/v1/artists/6n4SsAp5VjvIBg3s9QCcPX","id":"6n4SsAp5VjvIBg3s9QCcPX","name":"Masaki Suda","type":"artist","uri":"spotify:artist:6n4SsAp5VjvIBg3s9QCcPX","count":2},{"external_urls":{"spotify":"https://open.spotify.com/artist/706WzkJEacBrtkHKRpBU2q"},"href":"https://api.spotify.com/v1/artists/706WzkJEacBrtkHKRpBU2q","id":"706WzkJEacBrtkHKRpBU2q","name":"Motohiro Hata","type":"artist","uri":"spotify:artist:706WzkJEacBrtkHKRpBU2q","count":2},{"external_urls":{"spotify":"https://open.spotify.com/artist/0hCWVMGGQnRVfDgmhwLIxq"},"href":"https://api.spotify.com/v1/artists/0hCWVMGGQnRVfDgmhwLIxq","id":"0hCWVMGGQnRVfDgmhwLIxq","name":"Sakanaction","type":"artist","uri":"spotify:artist:0hCWVMGGQnRVfDgmhwLIxq","count":2}],"features":{"danceability":0.5049414781719951,"energy":0.8891905866034249,"key":5.298866072258592,"loudness":-3.133561426603994,"mode":0.9349974091164768,"speechiness":0.061451070533177256,"acousticness":0.05833221616075625,"instrumentalness":0.00003499682748941705,"liveness":0.2082015670266196,"valence":0.5672763321953793,"tempo":138.0737179980066}}