{"idx":"33","name":"Lithuania","id":"37i9dQZEVXbMx56Rdq5lwc","genres":[{"name":"pop","count":38},{"name":"dance pop","count":17},{"name":"post-teen pop","count":12},{"name":"edm","count":8},{"name":"pop rap","count":7},{"name":"rap","count":7},{"name":"tropical house","count":7}],"artists":[{"external_urls":{"spotify":"https://open.spotify.com/artist/246dkjvS1zLTtiykXe5h60"},"href":"https://api.spotify.com/v1/artists/246dkjvS1zLTtiykXe5h60","id":"246dkjvS1zLTtiykXe5h60","name":"Post Malone","type":"artist","uri":"spotify:artist:246dkjvS1zLTtiykXe5h60","count":7},{"external_urls":{"spotify":"https://open.spotify.com/artist/6qqNVTkY8uBg9cP3Jd7DAH"},"href":"https://api.spotify.com/v1/artists/6qqNVTkY8uBg9cP3Jd7DAH","id":"6qqNVTkY8uBg9cP3Jd7DAH","name":"Billie Eilish","type":"artist","uri":"spotify:artist:6qqNVTkY8uBg9cP3Jd7DAH","count":3},{"external_urls":{"spotify":"https://open.spotify.com/artist/4nDoRrQiYLoBzwC5BhVJzF"},"href":"https://api.spotify.com/v1/artists/4nDoRrQiYLoBzwC5BhVJzF","id":"4nDoRrQiYLoBzwC5BhVJzF","name":"Camila Cabello","type":"artist","uri":"spotify:artist:4nDoRrQiYLoBzwC5BhVJzF","count":3},{"external_urls":{"spotify":"https://open.spotify.com/artist/66CXWjxzNUsdJxJ2JdwvnR"},"href":"https://api.spotify.com/v1/artists/66CXWjxzNUsdJxJ2JdwvnR","id":"66CXWjxzNUsdJxJ2JdwvnR","name":"Ariana Grande","type":"artist","uri":"spotify:artist:66CXWjxzNUsdJxJ2JdwvnR","count":2},{"external_urls":{"spotify":"https://open.spotify.com/artist/6eUKZXaKkcviH0Ku9w2n3V"},"href":"https://api.spotify.com/v1/artists/6eUKZXaKkcviH0Ku9w2n3V","id":"6eUKZXaKkcviH0Ku9w2n3V","name":"Ed Sheeran","type":"artist","uri":"spotify:artist:6eUKZXaKkcviH0Ku9w2n3V","count":2},{"external_urls":{"spotify":"https://open.spotify.com/artist/7jVv8c5Fj3E9VhNjxT4snq"},"href":"https://api.spotify.com/v1/artists/7jVv8c5Fj3E9VhNjxT4snq","id":"7jVv8c5Fj3E9VhNjxT4snq","name":"Lil Nas X","type":"artist","uri":"spotify:artist:7jVv8c5Fj3E9VhNjxT4snq","count":2},{"external_urls":{"spotify":"https://open.spotify.com/artist/56oDRnqbIiwx4mymNEv7dS"},"href":"https://api.spotify.com/v1/artists/56oDRnqbIiwx4mymNEv7dS","id":"56oDRnqbIiwx4mymNEv7dS","name":"Lizzo","type":"artist","uri":"spotify:artist:56oDRnqbIiwx4mymNEv7dS","count":2},{"external_urls":{"spotify":"https://open.spotify.com/artist/5YGY8feqx7naU7z4HrwZM6"},"href":"https://api.spotify.com/v1/artists/5YGY8feqx7naU7z4HrwZM6","id":"5YGY8feqx7naU7z4HrwZM6","name":"Miley Cyrus","type":"artist","uri":"spotify:artist:5YGY8feqx7naU7z4HrwZM6","count":2}],"features":[{"name":"danceability","value":0.6443733930160018},{"name":"energy","value":0.39190997856249843},{"name":"key","value":7.78108643551321},{"name":"loudness","value":-8.537176370175798},{"name":"mode","value":0.41659800959242155},{"name":"speechiness","value":0.0598150778127676},{"name":"acousticness","value":0.47831530540880046},{"name":"instrumentalness","value":0.00015097304562846001},{"name":"liveness","value":0.15250238709384173},{"name":"valence","value":0.35138967841190955},{"name":"tempo","value":100.53411640483026}]}