{"name":"Switzerland","id":"37i9dQZEVXbJiyhoAPEfMK","genres":[{"name":"pop","count":27},{"name":"german hip hop","count":14},{"name":"dance pop","count":8},{"name":"rap","count":7},{"name":"pop rap","count":6},{"name":"post-teen pop","count":6},{"name":"electropop","count":4},{"name":"reggaeton","count":4},{"name":"canadian pop","count":3},{"name":"edm","count":3},{"name":"trap","count":3},{"name":"uk pop","count":3},{"name":"canadian hip hop","count":2},{"name":"german cloud rap","count":2},{"name":"german pop","count":2},{"name":"hip hop","count":2},{"name":"latin","count":2},{"name":"melodic rap","count":2},{"name":"trap latino","count":2},{"name":"tropical house","count":2},{"name":"atl hip hop","count":1},{"name":"atl trap","count":1},{"name":"australian pop","count":1},{"name":"chicago rap","count":1},{"name":"dark trap","count":1},{"name":"deep german hip hop","count":1},{"name":"dfw rap","count":1},{"name":"electronic trap","count":1},{"name":"french hip hop","count":1},{"name":"gangster rap","count":1},{"name":"hamburg hip hop","count":1},{"name":"hollywood","count":1},{"name":"italian arena pop","count":1},{"name":"italian pop","count":1},{"name":"latin hip hop","count":1},{"name":"neo mellow","count":1},{"name":"piano rock","count":1},{"name":"pop house","count":1},{"name":"pop rock","count":1},{"name":"pop urbaine","count":1},{"name":"puerto rican pop","count":1},{"name":"reggaeton flow","count":1},{"name":"tropical","count":1},{"name":"uk dance","count":1},{"name":"vapor trap","count":1},{"name":"viral pop","count":1}],"artists":[{"external_urls":{"spotify":"https://open.spotify.com/artist/1qQLhymHXFPtP5U8KNKsm6"},"href":"https://api.spotify.com/v1/artists/1qQLhymHXFPtP5U8KNKsm6","id":"1qQLhymHXFPtP5U8KNKsm6","name":"Apache 207","type":"artist","uri":"spotify:artist:1qQLhymHXFPtP5U8KNKsm6","count":5},{"external_urls":{"spotify":"https://open.spotify.com/artist/5K4W6rqBFWDnAN6FQUkS6x"},"href":"https://api.spotify.com/v1/artists/5K4W6rqBFWDnAN6FQUkS6x","id":"5K4W6rqBFWDnAN6FQUkS6x","name":"Kanye West","type":"artist","uri":"spotify:artist:5K4W6rqBFWDnAN6FQUkS6x","count":5},{"external_urls":{"spotify":"https://open.spotify.com/artist/4WZGDpNwrC0vNQyl9QzF7d"},"href":"https://api.spotify.com/v1/artists/4WZGDpNwrC0vNQyl9QzF7d","id":"4WZGDpNwrC0vNQyl9QzF7d","name":"Capital Bra","type":"artist","uri":"spotify:artist:4WZGDpNwrC0vNQyl9QzF7d","count":4},{"external_urls":{"spotify":"https://open.spotify.com/artist/6h1s4i4XKIYv4ErDelLDN0"},"href":"https://api.spotify.com/v1/artists/6h1s4i4XKIYv4ErDelLDN0","id":"6h1s4i4XKIYv4ErDelLDN0","name":"Samra","type":"artist","uri":"spotify:artist:6h1s4i4XKIYv4ErDelLDN0","count":4},{"external_urls":{"spotify":"https://open.spotify.com/artist/4nDoRrQiYLoBzwC5BhVJzF"},"href":"https://api.spotify.com/v1/artists/4nDoRrQiYLoBzwC5BhVJzF","id":"4nDoRrQiYLoBzwC5BhVJzF","name":"Camila Cabello","type":"artist","uri":"spotify:artist:4nDoRrQiYLoBzwC5BhVJzF","count":3},{"external_urls":{"spotify":"https://open.spotify.com/artist/6eUKZXaKkcviH0Ku9w2n3V"},"href":"https://api.spotify.com/v1/artists/6eUKZXaKkcviH0Ku9w2n3V","id":"6eUKZXaKkcviH0Ku9w2n3V","name":"Ed Sheeran","type":"artist","uri":"spotify:artist:6eUKZXaKkcviH0Ku9w2n3V","count":3},{"external_urls":{"spotify":"https://open.spotify.com/artist/1vyhD5VmyZ7KMfW5gqLgo5"},"href":"https://api.spotify.com/v1/artists/1vyhD5VmyZ7KMfW5gqLgo5","id":"1vyhD5VmyZ7KMfW5gqLgo5","name":"J Balvin","type":"artist","uri":"spotify:artist:1vyhD5VmyZ7KMfW5gqLgo5","count":3},{"external_urls":{"spotify":"https://open.spotify.com/artist/246dkjvS1zLTtiykXe5h60"},"href":"https://api.spotify.com/v1/artists/246dkjvS1zLTtiykXe5h60","id":"246dkjvS1zLTtiykXe5h60","name":"Post Malone","type":"artist","uri":"spotify:artist:246dkjvS1zLTtiykXe5h60","count":2},{"external_urls":{"spotify":"https://open.spotify.com/artist/0C8ZW7ezQVs4URX5aX7Kqx"},"href":"https://api.spotify.com/v1/artists/0C8ZW7ezQVs4URX5aX7Kqx","id":"0C8ZW7ezQVs4URX5aX7Kqx","name":"Selena Gomez","type":"artist","uri":"spotify:artist:0C8ZW7ezQVs4URX5aX7Kqx","count":2},{"external_urls":{"spotify":"https://open.spotify.com/artist/4rTv3Ejc7hKMtmoBOK1B4T"},"href":"https://api.spotify.com/v1/artists/4rTv3Ejc7hKMtmoBOK1B4T","id":"4rTv3Ejc7hKMtmoBOK1B4T","name":"Ali Gatie","type":"artist","uri":"spotify:artist:4rTv3Ejc7hKMtmoBOK1B4T","count":1},{"external_urls":{"spotify":"https://open.spotify.com/artist/4Mt1ci7cKg2DpDS5kJ5mHS"},"href":"https://api.spotify.com/v1/artists/4Mt1ci7cKg2DpDS5kJ5mHS","id":"4Mt1ci7cKg2DpDS5kJ5mHS","name":"Animus","type":"artist","uri":"spotify:artist:4Mt1ci7cKg2DpDS5kJ5mHS","count":1},{"external_urls":{"spotify":"https://open.spotify.com/artist/028lPW2NdWHdSPCkRkcyhd"},"href":"https://api.spotify.com/v1/artists/028lPW2NdWHdSPCkRkcyhd","id":"028lPW2NdWHdSPCkRkcyhd","name":"Ant Clemons","type":"artist","uri":"spotify:artist:028lPW2NdWHdSPCkRkcyhd","count":1},{"external_urls":{"spotify":"https://open.spotify.com/artist/2R21vXR83lH98kGeO99Y66"},"href":"https://api.spotify.com/v1/artists/2R21vXR83lH98kGeO99Y66","id":"2R21vXR83lH98kGeO99Y66","name":"Anuel AA","type":"artist","uri":"spotify:artist:2R21vXR83lH98kGeO99Y66","count":1},{"external_urls":{"spotify":"https://open.spotify.com/artist/13bDjug9N0pyv3ZUINjkDV"},"href":"https://api.spotify.com/v1/artists/13bDjug9N0pyv3ZUINjkDV","id":"13bDjug9N0pyv3ZUINjkDV","name":"Bausa","type":"artist","uri":"spotify:artist:13bDjug9N0pyv3ZUINjkDV","count":1},{"external_urls":{"spotify":"https://open.spotify.com/artist/2nftqfbLohpDYzY8VUlvbm"},"href":"https://api.spotify.com/v1/artists/2nftqfbLohpDYzY8VUlvbm","id":"2nftqfbLohpDYzY8VUlvbm","name":"Benji & Fede","type":"artist","uri":"spotify:artist:2nftqfbLohpDYzY8VUlvbm","count":1},{"external_urls":{"spotify":"https://open.spotify.com/artist/6qqNVTkY8uBg9cP3Jd7DAH"},"href":"https://api.spotify.com/v1/artists/6qqNVTkY8uBg9cP3Jd7DAH","id":"6qqNVTkY8uBg9cP3Jd7DAH","name":"Billie Eilish","type":"artist","uri":"spotify:artist:6qqNVTkY8uBg9cP3Jd7DAH","count":1},{"external_urls":{"spotify":"https://open.spotify.com/artist/1aS5tqEs9ci5P9KD9tZWa6"},"href":"https://api.spotify.com/v1/artists/1aS5tqEs9ci5P9KD9tZWa6","id":"1aS5tqEs9ci5P9KD9tZWa6","name":"Bonez MC","type":"artist","uri":"spotify:artist:1aS5tqEs9ci5P9KD9tZWa6","count":1},{"external_urls":{"spotify":"https://open.spotify.com/artist/4VIvfOurcf0vuLRxLkGnIG"},"href":"https://api.spotify.com/v1/artists/4VIvfOurcf0vuLRxLkGnIG","id":"4VIvfOurcf0vuLRxLkGnIG","name":"Bradley Cooper","type":"artist","uri":"spotify:artist:4VIvfOurcf0vuLRxLkGnIG","count":1},{"external_urls":{"spotify":"https://open.spotify.com/artist/3c96G4d2lUOxhomM2mby5S"},"href":"https://api.spotify.com/v1/artists/3c96G4d2lUOxhomM2mby5S","id":"3c96G4d2lUOxhomM2mby5S","name":"Bushido","type":"artist","uri":"spotify:artist:3c96G4d2lUOxhomM2mby5S","count":1},{"external_urls":{"spotify":"https://open.spotify.com/artist/4kYSro6naA4h99UJvo89HB"},"href":"https://api.spotify.com/v1/artists/4kYSro6naA4h99UJvo89HB","id":"4kYSro6naA4h99UJvo89HB","name":"Cardi B","type":"artist","uri":"spotify:artist:4kYSro6naA4h99UJvo89HB","count":1},{"external_urls":{"spotify":"https://open.spotify.com/artist/540vIaP2JwjQb9dm3aArA4"},"href":"https://api.spotify.com/v1/artists/540vIaP2JwjQb9dm3aArA4","id":"540vIaP2JwjQb9dm3aArA4","name":"DJ Snake","type":"artist","uri":"spotify:artist:540vIaP2JwjQb9dm3aArA4","count":1},{"external_urls":{"spotify":"https://open.spotify.com/artist/4VMYDCV2IEDYJArk749S6m"},"href":"https://api.spotify.com/v1/artists/4VMYDCV2IEDYJArk749S6m","id":"4VMYDCV2IEDYJArk749S6m","name":"Daddy Yankee","type":"artist","uri":"spotify:artist:4VMYDCV2IEDYJArk749S6m","count":1},{"external_urls":{"spotify":"https://open.spotify.com/artist/2JwyRtuXf2l6sTnSnGVIa1"},"href":"https://api.spotify.com/v1/artists/2JwyRtuXf2l6sTnSnGVIa1","id":"2JwyRtuXf2l6sTnSnGVIa1","name":"Farid Bang","type":"artist","uri":"spotify:artist:2JwyRtuXf2l6sTnSnGVIa1","count":1},{"external_urls":{"spotify":"https://open.spotify.com/artist/1lB3I3SI30v2ZOpR4XQqzJ"},"href":"https://api.spotify.com/v1/artists/1lB3I3SI30v2ZOpR4XQqzJ","id":"1lB3I3SI30v2ZOpR4XQqzJ","name":"Gambi","type":"artist","uri":"spotify:artist:1lB3I3SI30v2ZOpR4XQqzJ","count":1},{"external_urls":{"spotify":"https://open.spotify.com/artist/2nm38smINjms1LtczR0Cei"},"href":"https://api.spotify.com/v1/artists/2nm38smINjms1LtczR0Cei","id":"2nm38smINjms1LtczR0Cei","name":"Goodboys","type":"artist","uri":"spotify:artist:2nm38smINjms1LtczR0Cei","count":1},{"external_urls":{"spotify":"https://open.spotify.com/artist/6KImCVD70vtIoJWnq6nGn3"},"href":"https://api.spotify.com/v1/artists/6KImCVD70vtIoJWnq6nGn3","id":"6KImCVD70vtIoJWnq6nGn3","name":"Harry Styles","type":"artist","uri":"spotify:artist:6KImCVD70vtIoJWnq6nGn3","count":1},{"external_urls":{"spotify":"https://open.spotify.com/artist/45eNHdiiabvmbp4erw26rg"},"href":"https://api.spotify.com/v1/artists/45eNHdiiabvmbp4erw26rg","id":"45eNHdiiabvmbp4erw26rg","name":"ILLENIUM","type":"artist","uri":"spotify:artist:45eNHdiiabvmbp4erw26rg","count":1},{"external_urls":{"spotify":"https://open.spotify.com/artist/1uNFoZAHBGtllmzznpCI3s"},"href":"https://api.spotify.com/v1/artists/1uNFoZAHBGtllmzznpCI3s","id":"1uNFoZAHBGtllmzznpCI3s","name":"Justin Bieber","type":"artist","uri":"spotify:artist:1uNFoZAHBGtllmzznpCI3s","count":1},{"external_urls":{"spotify":"https://open.spotify.com/artist/790FomKkXshlbRYZFtlgla"},"href":"https://api.spotify.com/v1/artists/790FomKkXshlbRYZFtlgla","id":"790FomKkXshlbRYZFtlgla","name":"KAROL G","type":"artist","uri":"spotify:artist:790FomKkXshlbRYZFtlgla","count":1},{"external_urls":{"spotify":"https://open.spotify.com/artist/6LuN9FCkKOj5PcnpouEgny"},"href":"https://api.spotify.com/v1/artists/6LuN9FCkKOj5PcnpouEgny","id":"6LuN9FCkKOj5PcnpouEgny","name":"Khalid","type":"artist","uri":"spotify:artist:6LuN9FCkKOj5PcnpouEgny","count":1},{"external_urls":{"spotify":"https://open.spotify.com/artist/23fqKkggKUBHNkbKtXEls4"},"href":"https://api.spotify.com/v1/artists/23fqKkggKUBHNkbKtXEls4","id":"23fqKkggKUBHNkbKtXEls4","name":"Kygo","type":"artist","uri":"spotify:artist:23fqKkggKUBHNkbKtXEls4","count":1},{"external_urls":{"spotify":"https://open.spotify.com/artist/5Yo5iU2nf4H41waPl4ZnS1"},"href":"https://api.spotify.com/v1/artists/5Yo5iU2nf4H41waPl4ZnS1","id":"5Yo5iU2nf4H41waPl4ZnS1","name":"LEA","type":"artist","uri":"spotify:artist:5Yo5iU2nf4H41waPl4ZnS1","count":1},{"external_urls":{"spotify":"https://open.spotify.com/artist/1HY2Jd0NmPuamShAr6KMms"},"href":"https://api.spotify.com/v1/artists/1HY2Jd0NmPuamShAr6KMms","id":"1HY2Jd0NmPuamShAr6KMms","name":"Lady Gaga","type":"artist","uri":"spotify:artist:1HY2Jd0NmPuamShAr6KMms","count":1},{"external_urls":{"spotify":"https://open.spotify.com/artist/1cZQSpDsxgKIX2yW5OR9Ot"},"href":"https://api.spotify.com/v1/artists/1cZQSpDsxgKIX2yW5OR9Ot","id":"1cZQSpDsxgKIX2yW5OR9Ot","name":"Lennon Stella","type":"artist","uri":"spotify:artist:1cZQSpDsxgKIX2yW5OR9Ot","count":1},{"external_urls":{"spotify":"https://open.spotify.com/artist/4GNC7GD6oZMSxPGyXy4MNB"},"href":"https://api.spotify.com/v1/artists/4GNC7GD6oZMSxPGyXy4MNB","id":"4GNC7GD6oZMSxPGyXy4MNB","name":"Lewis Capaldi","type":"artist","uri":"spotify:artist:4GNC7GD6oZMSxPGyXy4MNB","count":1},{"external_urls":{"spotify":"https://open.spotify.com/artist/0xRXCcSX89eobfrshSVdyu"},"href":"https://api.spotify.com/v1/artists/0xRXCcSX89eobfrshSVdyu","id":"0xRXCcSX89eobfrshSVdyu","name":"MEDUZA","type":"artist","uri":"spotify:artist:0xRXCcSX89eobfrshSVdyu","count":1},{"external_urls":{"spotify":"https://open.spotify.com/artist/04gDigrS5kc9YWfZHwBETP"},"href":"https://api.spotify.com/v1/artists/04gDigrS5kc9YWfZHwBETP","id":"04gDigrS5kc9YWfZHwBETP","name":"Maroon 5","type":"artist","uri":"spotify:artist:04gDigrS5kc9YWfZHwBETP","count":1},{"external_urls":{"spotify":"https://open.spotify.com/artist/5Pwc4xIPtQLFEnJriah9YJ"},"href":"https://api.spotify.com/v1/artists/5Pwc4xIPtQLFEnJriah9YJ","id":"5Pwc4xIPtQLFEnJriah9YJ","name":"OneRepublic","type":"artist","uri":"spotify:artist:5Pwc4xIPtQLFEnJriah9YJ","count":1},{"external_urls":{"spotify":"https://open.spotify.com/artist/1i8SpTcr7yvPOmcqrbnVXY"},"href":"https://api.spotify.com/v1/artists/1i8SpTcr7yvPOmcqrbnVXY","id":"1i8SpTcr7yvPOmcqrbnVXY","name":"Ozuna","type":"artist","uri":"spotify:artist:1i8SpTcr7yvPOmcqrbnVXY","count":1},{"external_urls":{"spotify":"https://open.spotify.com/artist/0Dvx6p8JDyzeOPGmaCIH1L"},"href":"https://api.spotify.com/v1/artists/0Dvx6p8JDyzeOPGmaCIH1L","id":"0Dvx6p8JDyzeOPGmaCIH1L","name":"RAF Camora","type":"artist","uri":"spotify:artist:0Dvx6p8JDyzeOPGmaCIH1L","count":1},{"external_urls":{"spotify":"https://open.spotify.com/artist/18ISxWwWjV6rPLoVCXf1dz"},"href":"https://api.spotify.com/v1/artists/18ISxWwWjV6rPLoVCXf1dz","id":"18ISxWwWjV6rPLoVCXf1dz","name":"RIN","type":"artist","uri":"spotify:artist:18ISxWwWjV6rPLoVCXf1dz","count":1},{"external_urls":{"spotify":"https://open.spotify.com/artist/4ofCBoyEiGSePFAG500xev"},"href":"https://api.spotify.com/v1/artists/4ofCBoyEiGSePFAG500xev","id":"4ofCBoyEiGSePFAG500xev","name":"Regard","type":"artist","uri":"spotify:artist:4ofCBoyEiGSePFAG500xev","count":1},{"external_urls":{"spotify":"https://open.spotify.com/artist/2wY79sveU1sp5g7SokKOiI"},"href":"https://api.spotify.com/v1/artists/2wY79sveU1sp5g7SokKOiI","id":"2wY79sveU1sp5g7SokKOiI","name":"Sam Smith","type":"artist","uri":"spotify:artist:2wY79sveU1sp5g7SokKOiI","count":1},{"external_urls":{"spotify":"https://open.spotify.com/artist/7n2wHs1TKAczGzO7Dd2rGr"},"href":"https://api.spotify.com/v1/artists/7n2wHs1TKAczGzO7Dd2rGr","id":"7n2wHs1TKAczGzO7Dd2rGr","name":"Shawn Mendes","type":"artist","uri":"spotify:artist:7n2wHs1TKAczGzO7Dd2rGr","count":1},{"external_urls":{"spotify":"https://open.spotify.com/artist/4Yttlv9ndGjCDCVLqM7ACq"},"href":"https://api.spotify.com/v1/artists/4Yttlv9ndGjCDCVLqM7ACq","id":"4Yttlv9ndGjCDCVLqM7ACq","name":"Sido","type":"artist","uri":"spotify:artist:4Yttlv9ndGjCDCVLqM7ACq","count":1},{"external_urls":{"spotify":"https://open.spotify.com/artist/3drqpTL4sQOckmAfF9i1wg"},"href":"https://api.spotify.com/v1/artists/3drqpTL4sQOckmAfF9i1wg","id":"3drqpTL4sQOckmAfF9i1wg","name":"Summer Cem","type":"artist","uri":"spotify:artist:3drqpTL4sQOckmAfF9i1wg","count":1},{"external_urls":{"spotify":"https://open.spotify.com/artist/1yxSLGMDHlW21z4YXirZDS"},"href":"https://api.spotify.com/v1/artists/1yxSLGMDHlW21z4YXirZDS","id":"1yxSLGMDHlW21z4YXirZDS","name":"The Black Eyed Peas","type":"artist","uri":"spotify:artist:1yxSLGMDHlW21z4YXirZDS","count":1},{"external_urls":{"spotify":"https://open.spotify.com/artist/69GGBxA162lTqCwzJG5jLp"},"href":"https://api.spotify.com/v1/artists/69GGBxA162lTqCwzJG5jLp","id":"69GGBxA162lTqCwzJG5jLp","name":"The Chainsmokers","type":"artist","uri":"spotify:artist:69GGBxA162lTqCwzJG5jLp","count":1},{"external_urls":{"spotify":"https://open.spotify.com/artist/3pVfscwg2QxhdHtk966inb"},"href":"https://api.spotify.com/v1/artists/3pVfscwg2QxhdHtk966inb","id":"3pVfscwg2QxhdHtk966inb","name":"The Cratez","type":"artist","uri":"spotify:artist:3pVfscwg2QxhdHtk966inb","count":1},{"external_urls":{"spotify":"https://open.spotify.com/artist/2NjfBq1NflQcKSeiDooVjY"},"href":"https://api.spotify.com/v1/artists/2NjfBq1NflQcKSeiDooVjY","id":"2NjfBq1NflQcKSeiDooVjY","name":"Tones and I","type":"artist","uri":"spotify:artist:2NjfBq1NflQcKSeiDooVjY","count":1},{"external_urls":{"spotify":"https://open.spotify.com/artist/0Y5tJX1MQlPlqiwlOH1tJY"},"href":"https://api.spotify.com/v1/artists/0Y5tJX1MQlPlqiwlOH1tJY","id":"0Y5tJX1MQlPlqiwlOH1tJY","name":"Travis Scott","type":"artist","uri":"spotify:artist:0Y5tJX1MQlPlqiwlOH1tJY","count":1},{"external_urls":{"spotify":"https://open.spotify.com/artist/7c0XG5cIJTrrAgEC3ULPiq"},"href":"https://api.spotify.com/v1/artists/7c0XG5cIJTrrAgEC3ULPiq","id":"7c0XG5cIJTrrAgEC3ULPiq","name":"Ty Dolla $ign","type":"artist","uri":"spotify:artist:7c0XG5cIJTrrAgEC3ULPiq","count":1},{"external_urls":{"spotify":"https://open.spotify.com/artist/5LHRHt1k9lMyONurDHEdrp"},"href":"https://api.spotify.com/v1/artists/5LHRHt1k9lMyONurDHEdrp","id":"5LHRHt1k9lMyONurDHEdrp","name":"Tyga","type":"artist","uri":"spotify:artist:5LHRHt1k9lMyONurDHEdrp","count":1},{"external_urls":{"spotify":"https://open.spotify.com/artist/6XpaIBNiVzIetEPCWDvAFP"},"href":"https://api.spotify.com/v1/artists/6XpaIBNiVzIetEPCWDvAFP","id":"6XpaIBNiVzIetEPCWDvAFP","name":"Whitney Houston","type":"artist","uri":"spotify:artist:6XpaIBNiVzIetEPCWDvAFP","count":1},{"external_urls":{"spotify":"https://open.spotify.com/artist/6USMTwO0MNDnKte5a5h0xx"},"href":"https://api.spotify.com/v1/artists/6USMTwO0MNDnKte5a5h0xx","id":"6USMTwO0MNDnKte5a5h0xx","name":"Y2K","type":"artist","uri":"spotify:artist:6USMTwO0MNDnKte5a5h0xx","count":1},{"external_urls":{"spotify":"https://open.spotify.com/artist/50co4Is1HCEo8bhOyUWKpn"},"href":"https://api.spotify.com/v1/artists/50co4Is1HCEo8bhOyUWKpn","id":"50co4Is1HCEo8bhOyUWKpn","name":"Young Thug","type":"artist","uri":"spotify:artist:50co4Is1HCEo8bhOyUWKpn","count":1},{"external_urls":{"spotify":"https://open.spotify.com/artist/41X1TR6hrK8Q2ZCpp2EqCz"},"href":"https://api.spotify.com/v1/artists/41X1TR6hrK8Q2ZCpp2EqCz","id":"41X1TR6hrK8Q2ZCpp2EqCz","name":"bbno$","type":"artist","uri":"spotify:artist:41X1TR6hrK8Q2ZCpp2EqCz","count":1},{"external_urls":{"spotify":"https://open.spotify.com/artist/2cFrymmkijnjDg9SS92EPM"},"href":"https://api.spotify.com/v1/artists/2cFrymmkijnjDg9SS92EPM","id":"2cFrymmkijnjDg9SS92EPM","name":"blackbear","type":"artist","uri":"spotify:artist:2cFrymmkijnjDg9SS92EPM","count":1},{"external_urls":{"spotify":"https://open.spotify.com/artist/1ul8iLt2WnFe2UIyovjg7q"},"href":"https://api.spotify.com/v1/artists/1ul8iLt2WnFe2UIyovjg7q","id":"1ul8iLt2WnFe2UIyovjg7q","name":"reezy","type":"artist","uri":"spotify:artist:1ul8iLt2WnFe2UIyovjg7q","count":1}],"features":[{"name":"danceability","value":0.6888596166233132},{"name":"energy","value":0.5680715282339157},{"name":"key","value":7.068393025904925},{"name":"loudness","value":-7.030842274647876},{"name":"mode","value":0.8297797452070199},{"name":"speechiness","value":0.05152760542883872},{"name":"acousticness","value":0.20612929368874533},{"name":"instrumentalness","value":0.00020091330602665846},{"name":"liveness","value":0.4509273166732898},{"name":"valence","value":0.5187818629986185},{"name":"tempo","value":113.63122423279202}]}